cpybca/__init__.py
cpybca/bca.py
Cpybca-1.2.0.dist-info/LICENSE
Cpybca-1.2.0.dist-info/METADATA
Cpybca-1.2.0.dist-info/WHEEL
Cpybca-1.2.0.dist-info/top_level.txt
Cpybca-1.2.0.dist-info/RECORD
