Metadata-Version: 2.1
Name: Cpybca
Version: 1.2.0
Summary: A python module to access BCA API. In this version, you can check balance, account statement (history), and transfer fund.
Home-page: https://github.com/3mp3ri0r/cpybca/
Author: Christoforus Surjoputro
Author-email: cs_sanmar@yahoo.com
License: MIT
Platform: any
Classifier: Development Status :: 5 - Production/Stable
Classifier: Environment :: Plugins
Classifier: Intended Audience :: Developers
Classifier: License :: OSI Approved :: MIT License
Classifier: Operating System :: OS Independent
Classifier: Programming Language :: Python
Classifier: Programming Language :: Python :: 3
Classifier: Programming Language :: Python :: 3.3
Classifier: Programming Language :: Python :: 3.4
Classifier: Programming Language :: Python :: 3.5
Classifier: Programming Language :: Python :: 3.6
Classifier: Topic :: Office/Business :: Financial
Classifier: Topic :: Software Development :: Libraries :: Python Modules
Requires-Python: ~=3.3
Provides-Extra: dev
Requires-Dist: nose ; extra == 'dev'
